README.md
setup.cfg
setup.py
mkdocs_simple_tags_plugin.egg-info/PKG-INFO
mkdocs_simple_tags_plugin.egg-info/SOURCES.txt
mkdocs_simple_tags_plugin.egg-info/dependency_links.txt
mkdocs_simple_tags_plugin.egg-info/entry_points.txt
mkdocs_simple_tags_plugin.egg-info/requires.txt
mkdocs_simple_tags_plugin.egg-info/top_level.txt
tags/__init__.py
tags/plugin.py
tags/templates/tags.md.template