Metadata-Version: 2.1
Name: mkdocs-simple-tags-plugin
Version: 0.5
Summary: "Create tags in mkdocs"
Home-page: https://github.com/BeyondIM/mkdocs-simple-tags-plugin
Author: BeyondIM
Author-email: lypdarling@gmail.com
License: MIT
Keywords: "mkdocs python markdown tags"
Platform: UNKNOWN
Classifier: Intended Audience :: Developers
Classifier: License :: OSI Approved :: MIT License
Classifier: Operating System :: OS Independent
Classifier: Intended Audience :: Information Technology
Classifier: Programming Language :: Python :: 3.6
Classifier: Programming Language :: Python :: 3.7
Classifier: Programming Language :: Python :: 3.8
Classifier: Topic :: Security :: Cryptography
Requires-Python: >=3.8
